dep_hallucinator/cache_manager.py
dep_hallucinator/cli_config.py
dep_hallucinator/completion.py
dep_hallucinator/credential_security_guide.py
dep_hallucinator/dependency.py
dep_hallucinator/dependency_resolver.py
dep_hallucinator/error_handling.py
dep_hallucinator/forensic_manager.py
dep_hallucinator/forensic_reporting.py
dep_hallucinator/heuristics.py
dep_hallucinator/main.py
dep_hallucinator/ml_engine.py
dep_hallucinator/package_lists.py
dep_hallucinator/parsers.py
dep_hallucinator/performance_optimizer.py
dep_hallucinator/registry_clients.py
dep_hallucinator/reporting.py
dep_hallucinator/sbom_generator.py
dep_hallucinator/scanner.py
dep_hallucinator/signature_verification.py
dep_hallucinator/structured_logging.py
dep_hallucinator-1.0.1.dist-info/licenses/LICENSE
dep_hallucinator-1.0.1.dist-info/METADATA
dep_hallucinator-1.0.1.dist-info/WHEEL
dep_hallucinator-1.0.1.dist-info/entry_points.txt
dep_hallucinator-1.0.1.dist-info/top_level.txt
dep_hallucinator-1.0.1.dist-info/RECORD
