Metadata-Version: 2.4
Name: dep-hallucinator
Version: 1.0.1
Summary: Advanced security scanner for detecting AI-generated dependency confusion vulnerabilities with signature verification support
Author-email: Serhan <serhan.buyukbay@gmail.com>
License: MIT
Project-URL: Homepage, https://github.com/serhanwbahar/dep-hallucinator
Project-URL: Documentation, https://github.com/serhanwbahar/dep-hallucinator#readme
Project-URL: Repository, https://github.com/serhanwbahar/dep-hallucinator
Project-URL: Bug Reports, https://github.com/serhanwbahar/dep-hallucinator/issues
Project-URL: Changelog, https://github.com/serhanwbahar/dep-hallucinator/releases
Keywords: security,dependency,vulnerability,scanner,ai,hallucination
Classifier: Development Status :: 5 - Production/Stable
Classifier: Environment :: Console
Classifier: Intended Audience :: Developers
Classifier: Intended Audience :: System Administrators
Classifier: License :: OSI Approved :: MIT License
Classifier: Operating System :: OS Independent
Classifier: Programming Language :: Python :: 3
Classifier: Programming Language :: Python :: 3.8
Classifier: Programming Language :: Python :: 3.9
Classifier: Programming Language :: Python :: 3.10
Classifier: Programming Language :: Python :: 3.11
Classifier: Programming Language :: Python :: 3.12
Classifier: Topic :: Security
Classifier: Topic :: Software Development :: Quality Assurance
Classifier: Topic :: System :: Systems Administration
Requires-Python: >=3.8
License-File: LICENSE
Requires-Dist: click>=8.0.0
Requires-Dist: httpx[http2]>=0.24.0
Requires-Dist: structlog>=23.0.0
Requires-Dist: toml>=0.10.0
Requires-Dist: rich
Provides-Extra: rich
Requires-Dist: rich>=13.0.0; extra == "rich"
Provides-Extra: full
Requires-Dist: rich>=13.0.0; extra == "full"
Requires-Dist: numpy>=1.20.0; (platform_machine != "arm64" or python_version >= "3.9") and extra == "full"
Requires-Dist: scikit-learn>=1.0.0; (platform_machine != "arm64" or python_version >= "3.9") and extra == "full"
Provides-Extra: production
Requires-Dist: uvloop>=0.17.0; sys_platform != "win32" and extra == "production"
Requires-Dist: orjson>=3.8.0; extra == "production"
Requires-Dist: lz4>=4.0.0; extra == "production"
Provides-Extra: dev
Requires-Dist: pytest>=7.0.0; extra == "dev"
Requires-Dist: pytest-asyncio>=0.21.0; extra == "dev"
Requires-Dist: pytest-httpx>=0.21.0; extra == "dev"
Requires-Dist: pytest-cov>=4.0.0; extra == "dev"
Requires-Dist: black>=23.0.0; extra == "dev"
Requires-Dist: mypy>=1.0.0; extra == "dev"
Requires-Dist: ruff>=0.1.0; extra == "dev"
Requires-Dist: bandit>=1.7.0; extra == "dev"
Requires-Dist: safety>=3.0.0; extra == "dev"
Requires-Dist: build>=0.10.0; extra == "dev"
Requires-Dist: twine>=4.0.0; extra == "dev"
Requires-Dist: rich>=13.0.0; extra == "dev"
Provides-Extra: test
Requires-Dist: pytest>=7.0.0; extra == "test"
Requires-Dist: pytest-asyncio>=0.21.0; extra == "test"
Requires-Dist: pytest-httpx>=0.21.0; extra == "test"
Requires-Dist: pytest-cov>=4.0.0; extra == "test"
Requires-Dist: coverage>=7.0.0; extra == "test"
Requires-Dist: pytest-benchmark>=4.0.0; extra == "test"
Requires-Dist: memory-profiler>=0.60.0; extra == "test"
Requires-Dist: ruff>=0.1.0; extra == "test"
Provides-Extra: resolvers
Requires-Dist: pipdeptree>=2.0.0; extra == "resolvers"
Requires-Dist: pip-tools>=6.0.0; extra == "resolvers"
Provides-Extra: security
Requires-Dist: bandit>=1.7.0; extra == "security"
Requires-Dist: safety>=3.0.0; extra == "security"
Provides-Extra: all
Requires-Dist: rich>=13.0.0; extra == "all"
Requires-Dist: numpy>=1.20.0; (platform_machine != "arm64" or python_version >= "3.9") and extra == "all"
Requires-Dist: scikit-learn>=1.0.0; (platform_machine != "arm64" or python_version >= "3.9") and extra == "all"
Requires-Dist: uvloop>=0.17.0; sys_platform != "win32" and extra == "all"
Requires-Dist: orjson>=3.8.0; extra == "all"
Requires-Dist: lz4>=4.0.0; extra == "all"
Dynamic: license-file
